django_json_ld/__init__.py
django_json_ld/settings.py
django_json_ld/util.py
django_json_ld/views.py
django_json_ld/templatetags/__init__.py
django_json_ld/templatetags/json_ld.py
django_json_ld-0.0.4.dist-info/LICENSE
django_json_ld-0.0.4.dist-info/METADATA
django_json_ld-0.0.4.dist-info/WHEEL
django_json_ld-0.0.4.dist-info/top_level.txt
django_json_ld-0.0.4.dist-info/RECORD
