Metadata-Version: 2.1
Name: django-json-ld
Version: 0.0.4
Summary: Django template tag for json-ld
Home-page: https://github.com/hiimdoublej/django-json-ld
Author: Johnny Chang
Author-email: hiimdoublej.pi@gmail.com
License: UNKNOWN
Keywords: django,webpack,assets
Platform: UNKNOWN
Classifier: Programming Language :: Python :: 3.6
Classifier: Framework :: Django
Classifier: Environment :: Web Environment
Classifier: License :: OSI Approved :: MIT License
